international/__init__.py
international/main.py
international-0.1.2.dist-info/METADATA
international-0.1.2.dist-info/WHEEL
international-0.1.2.dist-info/RECORD
